{"cameraMode":{"drawMode":0,"name":"Shaded","section":"Shading Mode"},"sceneLighting":false,"audioPlay":false,"sceneViewState":{"m_AlwaysRefresh":false,"showFog":true,"showSkybox":false,"showFlares":true,"showImageEffects":true,"showParticleSystems":true,"showVisualEffectGraphs":true,"m_FxEnabled":true},"in2DMode":false,"pivot":{"x":11.360000610351563,"y":-7.199999809265137,"z":-1.9500017166137696},"rotation":{"x":0.17109763622283936,"y":0.6152129173278809,"z":-0.13906444609165193,"w":0.7569071054458618},"size":34.35799026489258,"orthographic":true}